{"lang": "en_US", "eventid": "main_16", "eventName": "Abnormal Spectrum", "entryType": "MAINLINE", "storyCode": "EG-9", "avgTag": "Interlude", "storyName": "Homecoming", "storyInfo": "When the gunfire ceases and the screams grow quiet, I'll be back by my mother's side, like when I was born.\n", "storyList": [{"id": 0, "prop": "HEADER", "attributes": {"key": "title_test", "is_skippable": "true", "fit_mode": "BLACK_MASK"}}, {"id": 1, "prop": "Blocker", "attributes": {"a": 1.0, "r": 0.0, "g": 0.0, "b": 0.0, "fadetime": 0.0, "block": "true"}}, {"id": 2, "prop": "stopmusic", "attributes": {}}, {"id": 3, "prop": "Dialog", "attributes": {}}, {"id": 4, "prop": "Delay", "attributes": {"time": 1.0}}, {"id": 5, "prop": "Background", "attributes": {"image": "50_g13_warshipcommandroom", "screenadapt": "coverall"}}, {"id": 6, "prop": "Blocker", "attributes": {"a": 0.0, "r": 0.0, "g": 0.0, "b": 0.0, "fadetime": 1.0, "block": "true"}}, {"id": 7, "prop": "playMusic", "attributes": {"intro": "$darkness01_intro", "key": "$darkness01_loop", "volume": 0.6}}, {"id": 8, "prop": "Delay", "attributes": {"time": 2.0}}, {"id": 9, "prop": "playsound", "attributes": {"key": "$d_avg_telegraph_loop", "loop": "true", "channel": "bgs"}}, {"id": 10, "prop": "Delay", "attributes": {"time": 1.0}}, {"id": 11, "prop": "name", "attributes": {"content": "'All units, this is Dispatch.'"}}, {"id": 12, "prop": "name", "attributes": {"content": "'All units, cease fire immediately. We have an urgent request from Deity Grypherburg.'"}}, {"id": 13, "prop": "name", "attributes": {"content": "'Repeat, all units, cease fire immediately.'"}}, {"id": 14, "prop": "name", "attributes": {"content": "'Please acknowledge.'"}}, {"id": 15, "prop": "dialog", "attributes": {}}, {"id": 16, "prop": "Delay", "attributes": {"time": 1.0}}, {"id": 17, "prop": "charslot", "attributes": {"slot": "m", "name": "avg_npc_1977_1#1$1", "duration": 1.0}}, {"id": 18, "prop": "Delay", "attributes": {"time": 2.0}}, {"id": 19, "prop": "name", "attributes": {"content": "(Exhales)", "name": "Officer"}, "figure_art": "avg_npc_1977_1#1$1"}, {"id": 20, "prop": "name", "attributes": {"content": "Scope of the ceasefire?", "name": "Officer"}, "figure_art": "avg_npc_1977_1#1$1"}, {"id": 21, "prop": "charslot", "attributes": {"slot": "m", "focus": "n"}}, {"id": 22, "prop": "name", "attributes": {"content": "All active units.", "name": "Radioman"}}, {"id": 23, "prop": "charslot", "attributes": {"slot": "m", "name": "avg_npc_1977_1#1$1"}}, {"id": 24, "prop": "name", "attributes": {"content": "(Nods)", "name": "Officer"}, "figure_art": "avg_npc_1977_1#1$1"}, {"id": 25, "prop": "charslot", "attributes": {"slot": "m", "focus": "n"}}, {"id": 26, "prop": "name", "attributes": {"content": "'Acknowledged.'"}}, {"id": 27, "prop": "charslot", "attributes": {"slot": "m", "name": "avg_npc_1977_1#1$1"}}, {"id": 28, "prop": "name", "attributes": {"content": "Inform Lieutenant Yelchin and ensure that all units in the 2nd Division observe the ceasefire.", "name": "Officer"}, "figure_art": "avg_npc_1977_1#1$1"}, {"id": 29, "prop": "charslot", "attributes": {"slot": "m", "focus": "n"}}, {"id": 30, "prop": "name", "attributes": {"content": "'All units remain on standby. Maintain battle stations.'"}}, {"id": 31, "prop": "name", "attributes": {"content": "'Until the threat is completely eliminated, we shall continue to serve our duty to protect Deity Grypherburg and the people.'"}}, {"id": 32, "prop": "Dialog", "attributes": {}}, {"id": 33, "prop": "playsound", "attributes": {"key": "$p_imp_funnel_end_h"}}, {"id": 34, "prop": "StopSound", "attributes": {"channel": "bgs", "fadetime": 1.0}}, {"id": 35, "prop": "Delay", "attributes": {"time": 2.0}}, {"id": 36, "prop": "charslot", "attributes": {"slot": "m", "name": "avg_npc_1977_1#1$1"}}, {"id": 37, "prop": "name", "attributes": {"content": "...Summon the quartermaster.", "name": "Officer"}, "figure_art": "avg_npc_1977_1#1$1"}, {"id": 38, "prop": "charslot", "attributes": {"slot": "m", "name": "avg_npc_1976_1#1$1"}}, {"id": 39, "prop": "name", "attributes": {"content": "Sir, we do not have a quartermaster for this operation.", "name": "Soldier"}, "figure_art": "avg_npc_1976_1#1$1"}, {"id": 40, "prop": "name", "attributes": {"content": "You expected this to be only a quick response, and that it would not take much time to eliminate the rebellious Infected.", "name": "Soldier"}, "figure_art": "avg_npc_1976_1#1$1"}, {"id": 41, "prop": "charslot", "attributes": {"slot": "m", "name": "avg_npc_1977_1#1$1"}}, {"id": 42, "prop": "name", "attributes": {"content": "......", "name": "Officer"}, "figure_art": "avg_npc_1977_1#1$1"}, {"id": 43, "prop": "name", "attributes": {"content": "Respond to Dispatch as usual.", "name": "Officer"}, "figure_art": "avg_npc_1977_1#1$1"}, {"id": 44, "prop": "name", "attributes": {"content": "And what is your name, soldier?", "name": "Officer"}, "figure_art": "avg_npc_1977_1#1$1"}, {"id": 45, "prop": "charslot", "attributes": {"slot": "m", "name": "avg_npc_1976_1#1$1"}}, {"id": 46, "prop": "name", "attributes": {"content": "Private Vyacheslav Kinov, sir.", "name": "Soldier"}, "figure_art": "avg_npc_1976_1#1$1"}, {"id": 47, "prop": "charslot", "attributes": {"slot": "m", "name": "avg_npc_1977_1#1$1"}}, {"id": 48, "prop": "name", "attributes": {"content": "Very well. Inform the Lieutenant, Private Kinov. Your services are not needed here for now.", "name": "Officer"}, "figure_art": "avg_npc_1977_1#1$1"}, {"id": 49, "prop": "Dialog", "attributes": {}}, {"id": 50, "prop": "Blocker", "attributes": {"a": 1.0, "r": 0.0, "g": 0.0, "b": 0.0, "fadetime": 2.0, "block": "true"}}, {"id": 51, "prop": "charslot", "attributes": {}}, {"id": 52, "prop": "delay", "attributes": {"time": 1.0}}, {"id": 53, "prop": "Background", "attributes": {"image": "bg_warehouse_2", "screenadapt": "coverall"}}, {"id": 54, "prop": "Blocker", "attributes": {"a": 0.0, "r": 0.0, "g": 0.0, "b": 0.0, "fadetime": 2.0, "block": "true"}}, {"id": 55, "prop": "delay", "attributes": {"time": 1.0}}, {"id": 56, "prop": "charslot", "attributes": {"slot": "m", "name": "avg_npc_1978_1#1$1", "duration": 1.0}}, {"id": 57, "prop": "Delay", "attributes": {"time": 2.0}}, {"id": 58, "prop": "name", "attributes": {"content": "...You had me leave my post to come to you for this little thing?", "name": "Cold Soldier"}, "figure_art": "avg_npc_1978_1#1$1"}, {"id": 59, "prop": "name", "attributes": {"content": "You're out of your mind.", "name": "Cold Soldier"}, "figure_art": "avg_npc_1978_1#1$1"}, {"id": 60, "prop": "dialog", "attributes": {}}, {"id": 61, "prop": "charslot", "attributes": {}}, {"id": 62, "prop": "charslot", "attributes": {"slot": "m", "name": "avg_npc_1976_1#1$1", "duration": 0.5}}, {"id": 63, "prop": "Delay", "attributes": {"time": 1.0}}, {"id": 64, "prop": "name", "attributes": {"content": "Oh, look at you, Patya, all high and mighty in that Shieldguard armor...", "name": "Angry Soldier"}, "figure_art": "avg_npc_1976_1#1$1"}, {"id": 65, "prop": "name", "attributes": {"content": "Does that pretty helmet of yours block your sight?", "name": "Angry Soldier"}, "figure_art": "avg_npc_1976_1#1$1"}, {"id": 66, "prop": "name", "attributes": {"content": "The maggots in the rations, bolts that snap like twigs, even duds!", "name": "Angry Soldier"}, "figure_art": "avg_npc_1976_1#1$1"}, {"id": 67, "prop": "name", "attributes": {"content": "Is this what they send us out to die with?!", "name": "Angry Soldier"}, "figure_art": "avg_npc_1976_1#1$1"}, {"id": 68, "prop": "charslot", "attributes": {"slot": "m", "name": "avg_npc_1978_1#1$1"}}, {"id": 69, "prop": "name", "attributes": {"content": "If there are maggots in your rations, you eat them with the rations. If the weapons are hard to use, use your bare hands.", "name": "Cold Soldier"}, "figure_art": "avg_npc_1978_1#1$1"}, {"id": 70, "prop": "name", "attributes": {"content": "We're soldiers. We fight and win. There are only two ends: Keep fighting, or die.", "name": "Cold Soldier"}, "figure_art": "avg_npc_1978_1#1$1"}, {"id": 71, "prop": "charslot", "attributes": {"slot": "m", "name": "avg_npc_1976_1#1$1"}}, {"id": 72, "prop": "name", "attributes": {"content": "You're the one who's out of his mind!", "name": "Angry Soldier"}, "figure_art": "avg_npc_1976_1#1$1"}, {"id": 73, "prop": "charslot", "attributes": {"slot": "m", "name": "avg_npc_1978_1#1$1"}}, {"id": 74, "prop": "name", "attributes": {"content": "If you find that someone hasn't been doing his job, you report to your superior, not complain to me here.", "name": "Cold Soldier"}, "figure_art": "avg_npc_1978_1#1$1"}, {"id": 75, "prop": "name", "attributes": {"content": "I'm not the quartermaster—", "name": "Cold Soldier"}, "figure_art": "avg_npc_1978_1#1$1"}, {"id": 76, "prop": "dialog", "attributes": {}}, {"id": 77, "prop": "charslot", "attributes": {}}, {"id": 78, "prop": "playsound", "attributes": {"key": "$d_avg_armyboots_walk", "loop": "true", "channel": "bgs"}}, {"id": 79, "prop": "charslot", "attributes": {"slot": "m", "name": "avg_npc_1977_1#1$1", "duration": 1.0}}, {"id": 80, "prop": "Delay", "attributes": {"time": 1.5}}, {"id": 81, "prop": "StopSound", "attributes": {"channel": "bgs", "fadetime": 0.3}}, {"id": 82, "prop": "Delay", "attributes": {"time": 0.5}}, {"id": 83, "prop": "name", "attributes": {"content": "I thought the Defender Regiments were supposed to be on the top deck.", "name": "Officer"}, "figure_art": "avg_npc_1977_1#1$1"}, {"id": 84, "prop": "charslot", "attributes": {"slot": "m", "name": "avg_npc_1978_1#1$1"}}, {"id": 85, "prop": "name", "attributes": {"content": "...Sorry, sir. I was away from my post.", "name": "Cold Soldier"}, "figure_art": "avg_npc_1978_1#1$1"}, {"id": 86, "prop": "name", "attributes": {"content": "I will report this to the commissar myself.", "name": "Cold Soldier"}, "figure_art": "avg_npc_1978_1#1$1"}, {"id": 87, "prop": "name", "attributes": {"content": "(Salutes)", "name": "Cold Soldier"}, "figure_art": "avg_npc_1978_1#1$1"}, {"id": 88, "prop": "dialog", "attributes": {}}, {"id": 89, "prop": "playsound", "attributes": {"key": "$d_avg_armour"}}, {"id": 90, "prop": "charslot", "attributes": {"duration": 1.0}}, {"id": 91, "prop": "Delay", "attributes": {"time": 2.5}}, {"id": 92, "prop": "charslot", "attributes": {}}, {"id": 93, "prop": "charslot", "attributes": {"slot": "m", "name": "avg_npc_1977_1#1$1"}}, {"id": 94, "prop": "name", "attributes": {"content": "......", "name": "Officer"}, "figure_art": "avg_npc_1977_1#1$1"}, {"id": 95, "prop": "charslot", "attributes": {"slot": "m", "name": "avg_npc_1976_1#1$1"}}, {"id": 96, "prop": "name", "attributes": {"content": "S-Sir!", "name": "Angry Soldier"}, "figure_art": "avg_npc_1976_1#1$1"}, {"id": 97, "prop": "charslot", "attributes": {"slot": "m", "name": "avg_npc_1977_1#1$1"}}, {"id": 98, "prop": "name", "attributes": {"content": "What did you find out, soldier?", "name": "Officer"}, "figure_art": "avg_npc_1977_1#1$1"}, {"id": 99, "prop": "name", "attributes": {"content": "Tell me the reason for your anger.", "name": "Officer"}, "figure_art": "avg_npc_1977_1#1$1"}, {"id": 100, "prop": "charslot", "attributes": {"slot": "m", "name": "avg_npc_1976_1#1$1"}}, {"id": 101, "prop": "name", "attributes": {"content": "...The quality of our supplies and equipment on this operation is exceedingly poor.", "name": "Angry Soldier"}, "figure_art": "avg_npc_1976_1#1$1"}, {"id": 102, "prop": "name", "attributes": {"content": "The rations are insufficient, the cans damaged and filled with maggots...", "name": "Angry Soldier"}, "figure_art": "avg_npc_1976_1#1$1"}, {"id": 103, "prop": "name", "attributes": {"content": "Many of the bolts were not made of steel, but crude iron.", "name": "Angry Soldier"}, "figure_art": "avg_npc_1976_1#1$1"}, {"id": 104, "prop": "name", "attributes": {"content": "And the reserve Originium bombs are so weak that they're little more than glorified duds.", "name": "Angry Soldier"}, "figure_art": "avg_npc_1976_1#1$1"}, {"id": 105, "prop": "name", "attributes": {"content": "How are we supposed to proceed the operation with these?", "name": "Angry Soldier"}, "figure_art": "avg_npc_1976_1#1$1"}, {"id": 106, "prop": "charslot", "attributes": {"slot": "m", "name": "avg_npc_1977_1#1$1"}}, {"id": 107, "prop": "name", "attributes": {"content": "Why did you enlist, soldier?", "name": "Officer"}, "figure_art": "avg_npc_1977_1#1$1"}, {"id": 108, "prop": "charslot", "attributes": {"slot": "m", "name": "avg_npc_1976_1#1$1"}}, {"id": 109, "prop": "name", "attributes": {"content": "To...", "name": "Angry Soldier"}, "figure_art": "avg_npc_1976_1#1$1"}, {"id": 110, "prop": "charslot", "attributes": {"slot": "m", "name": "avg_npc_1977_1#1$1"}}, {"id": 111, "prop": "name", "attributes": {"content": "Speak up.", "name": "Officer"}, "figure_art": "avg_npc_1977_1#1$1"}, {"id": 112, "prop": "charslot", "attributes": {"slot": "m", "name": "avg_npc_1976_1#1$1"}}, {"id": 113, "prop": "name", "attributes": {"content": "To—to prove myself! I want people to know my name—", "name": "Angry Soldier"}, "figure_art": "avg_npc_1976_1#1$1"}, {"id": 114, "prop": "name", "attributes": {"content": "Like they know yours!", "name": "Angry Soldier"}, "figure_art": "avg_npc_1976_1#1$1"}, {"id": 115, "prop": "charslot", "attributes": {"slot": "m", "name": "avg_npc_1977_1#1$1"}}, {"id": 116, "prop": "name", "attributes": {"content": "They'll know your name when the Army sends your tags back to your mother, and she etches them on a white birch tree.", "name": "Officer"}, "figure_art": "avg_npc_1977_1#1$1"}, {"id": 117, "prop": "charslot", "attributes": {"slot": "m", "name": "avg_npc_1976_1#1$1"}}, {"id": 118, "prop": "name", "attributes": {"content": "No, not like that...", "name": "Angry Soldier"}, "figure_art": "avg_npc_1976_1#1$1"}, {"id": 119, "prop": "charslot", "attributes": {"slot": "m", "name": "avg_npc_1977_1#1$1"}}, {"id": 120, "prop": "name", "attributes": {"content": "There is little room for the individual to choose, when the collective is at war.", "name": "Officer"}, "figure_art": "avg_npc_1977_1#1$1"}, {"id": 121, "prop": "name", "attributes": {"content": "But...", "name": "Officer"}, "figure_art": "avg_npc_1977_1#1$1"}, {"id": 122, "prop": "name", "attributes": {"content": "Keep this hope in your heart, boy, and your 'discovery' too.", "name": "Officer"}, "figure_art": "avg_npc_1977_1#1$1"}, {"id": 123, "prop": "name", "attributes": {"content": "For the survival of Ursus and her people, there is only one option...", "name": "Officer"}, "figure_art": "avg_npc_1977_1#1$1"}, {"id": 124, "prop": "Dialog", "attributes": {}}, {"id": 125, "prop": "Blocker", "attributes": {"a": 1.0, "r": 0.0, "g": 0.0, "b": 0.0, "fadetime": 2.0, "block": "true"}}, {"id": 126, "prop": "Delay", "attributes": {"time": 1.0}}, {"id": 127, "prop": "name", "attributes": {"content": "Set this land on fire.", "name": "Officer"}}, {"id": 128, "prop": "Dialog", "attributes": {}}, {"id": 129, "prop": "Delay", "attributes": {"time": 2.0}}, {"id": 130, "prop": "Blocker", "attributes": {"a": 1.0, "r": 0.0, "g": 0.0, "b": 0.0, "fadetime": 2.0, "block": "true"}}, {"id": 131, "prop": "stopmusic", "attributes": {"fadetime": 2.0}}, {"id": 132, "prop": "hidecgitem", "attributes": {}}, {"id": 133, "prop": "Image", "attributes": {}}, {"id": 134, "prop": "charslot", "attributes": {}}, {"id": 135, "prop": "name", "attributes": {"content": ""}}], "OPTIONTRACE": true}